LICENSE
MANIFEST.in
README
README.md
setup.py
expvar/__init__.py
expvar/stats.py
expvar/version.py
expvar.egg-info/PKG-INFO
expvar.egg-info/SOURCES.txt
expvar.egg-info/dependency_links.txt
expvar.egg-info/top_level.txt